<?xml version="1.0" encoding="utf-8"?>
<!DOCTYPE hibernate-mapping PUBLIC "-//Hibernate/Hibernate Mapping DTD 3.0//EN"
"http://hibernate.sourceforge.net/hibernate-mapping-3.0.dtd">
<!-- 
    Mapping file autogenerated by MyEclipse Persistence Tools
-->
<hibernate-mapping>
    <class name="com.ucuh.entity.Code" table="hchh_code" catalog="hchh">
        <composite-id name="id" class="com.ucuh.entity.CodeId">
            <key-property name="userKey" type="string">
                <column name="userKey" length="100" />
            </key-property>
            <key-property name="userCode" type="string">
                <column name="userCode" length="6" />
            </key-property>
            <key-property name="sendOverTime" type="timestamp">
                <column name="sendOverTime" length="19" />
            </key-property>
        </composite-id>
    </class>
</hibernate-mapping>
